interactive_dispatcher/__init__.py
interactive_dispatcher/interactive_dispatcher.py
interactive_dispatcher-1.0.2.dist-info/LICENSE
interactive_dispatcher-1.0.2.dist-info/METADATA
interactive_dispatcher-1.0.2.dist-info/WHEEL
interactive_dispatcher-1.0.2.dist-info/top_level.txt
interactive_dispatcher-1.0.2.dist-info/RECORD
