Metadata-Version: 2.1
Name: interactive-dispatcher
Version: 1.0.2
Summary: A customizable interactive CLI menu dispatcher with extendable return signals and matching function calls.
Author: Akhand Pratap Tiwari
License: Apache License
Project-URL: Homepage, https://github.com/Akhand-Pratap-Tiwari/python-interactive-dispatcher
Keywords: cli,menu,dispatcher,return-signal,customizable,interactive,function-calls
Classifier: Development Status :: 5 - Production/Stable
Classifier: Intended Audience :: Developers
Classifier: Topic :: Software Development :: User Interfaces
Classifier: Programming Language :: Python :: 3
Classifier: Operating System :: OS Independent
Requires-Python: >=3.8
License-File: LICENSE
Provides-Extra: dev
Requires-Dist: pytest; extra == "dev"
Requires-Dist: mypy; extra == "dev"
Requires-Dist: black; extra == "dev"
